odoo/addons/l10n_ro_account_bank_statement_import_mt940_brd/README.rst
odoo/addons/l10n_ro_account_bank_statement_import_mt940_brd/__init__.py
odoo/addons/l10n_ro_account_bank_statement_import_mt940_brd/__manifest__.py
odoo/addons/l10n_ro_account_bank_statement_import_mt940_brd/demo/demo_data.xml
odoo/addons/l10n_ro_account_bank_statement_import_mt940_brd/i18n/ca_ES.po
odoo/addons/l10n_ro_account_bank_statement_import_mt940_brd/i18n/de.po
odoo/addons/l10n_ro_account_bank_statement_import_mt940_brd/i18n/es.po
odoo/addons/l10n_ro_account_bank_statement_import_mt940_brd/i18n/fi.po
odoo/addons/l10n_ro_account_bank_statement_import_mt940_brd/i18n/fr.po
odoo/addons/l10n_ro_account_bank_statement_import_mt940_brd/i18n/fr_CH.po
odoo/addons/l10n_ro_account_bank_statement_import_mt940_brd/i18n/gl.po
odoo/addons/l10n_ro_account_bank_statement_import_mt940_brd/i18n/l10n_ro_account_bank_statement_import_mt940_brd.pot
odoo/addons/l10n_ro_account_bank_statement_import_mt940_brd/i18n/lt_LT.po
odoo/addons/l10n_ro_account_bank_statement_import_mt940_brd/i18n/nb_NO.po
odoo/addons/l10n_ro_account_bank_statement_import_mt940_brd/i18n/nl.po
odoo/addons/l10n_ro_account_bank_statement_import_mt940_brd/i18n/nl_NL.po
odoo/addons/l10n_ro_account_bank_statement_import_mt940_brd/i18n/pt_BR.po
odoo/addons/l10n_ro_account_bank_statement_import_mt940_brd/i18n/pt_PT.po
odoo/addons/l10n_ro_account_bank_statement_import_mt940_brd/i18n/sl.po
odoo/addons/l10n_ro_account_bank_statement_import_mt940_brd/models/__init__.py
odoo/addons/l10n_ro_account_bank_statement_import_mt940_brd/models/account_bank_statement_import.py
odoo/addons/l10n_ro_account_bank_statement_import_mt940_brd/models/mt940.py
odoo/addons/l10n_ro_account_bank_statement_import_mt940_brd/static/description/icon.png
odoo/addons/l10n_ro_account_bank_statement_import_mt940_brd/test_files/test_brd_940.txt
odoo/addons/l10n_ro_account_bank_statement_import_mt940_brd/tests/__init__.py
odoo11_addon_l10n_ro_account_bank_statement_import_mt940_brd-11.0.1.0.0.99.dev7.dist-info/METADATA
odoo11_addon_l10n_ro_account_bank_statement_import_mt940_brd-11.0.1.0.0.99.dev7.dist-info/WHEEL
odoo11_addon_l10n_ro_account_bank_statement_import_mt940_brd-11.0.1.0.0.99.dev7.dist-info/top_level.txt
odoo11_addon_l10n_ro_account_bank_statement_import_mt940_brd-11.0.1.0.0.99.dev7.dist-info/RECORD
